bing_website_finder/__init__.py
bing_website_finder/__main__.py
bing_website_finder/config.py
bing_website_finder/get_websites.py
bing_website_finder/obj.py
bing_website_finder/util.py
bing_website_finder/data/example_input_website_finder.csv
bing_website_finder/data/example_output_with_websites.csv
bwf-0.0.1.dist-info/LICENSE
bwf-0.0.1.dist-info/METADATA
bwf-0.0.1.dist-info/WHEEL
bwf-0.0.1.dist-info/entry_points.txt
bwf-0.0.1.dist-info/top_level.txt
bwf-0.0.1.dist-info/RECORD
