Metadata-Version: 2.1
Name: bwf
Version: 0.0.1
Summary: Bing Website Finder (bwf) adds websites to a list of company names from the commandline.
Home-page: https://please.buythingsfrom.us
Author: Robert Truxal
Author-email: rtruxal2020@outlook.com
License: MIT-like (see LICENCE file)
Platform: UNKNOWN
Classifier: Development Status :: 2 - Pre-Alpha
Classifier: Operating System :: OS Independent
Classifier: Programming Language :: Python :: 3.7
Classifier: Programming Language :: Python :: 3.8
Classifier: Programming Language :: Python :: 3 :: Only
Classifier: Environment :: Console
Classifier: Framework :: AsyncIO
Classifier: Natural Language :: English
Classifier: Natural Language :: Esperanto
Classifier: Topic :: Internet :: WWW/HTTP
Classifier: Topic :: Internet :: Name Service (DNS)
Classifier: Topic :: Internet :: WWW/HTTP :: Indexing/Search
Classifier: Topic :: Internet :: WWW/HTTP :: Site Management
Classifier: Topic :: Internet :: WWW/HTTP :: Site Management :: Link Checking
Requires-Python: >=3.7.0
Requires-Dist: aiohttp
Requires-Dist: pandas
